pylib_fftw3f/__init__.py
pylib_fftw3f/placeholder.cp36-win32.pyd
pylib_fftw3f/include/fftw3.f
pylib_fftw3f/include/fftw3.f03
pylib_fftw3f/include/fftw3.h
pylib_fftw3f/include/fftw3l.f03
pylib_fftw3f/include/fftw3q.f03
pylib_fftw3f/lib/fftw3f.lib
pylib_fftw3f/lib/cmake/fftw3f/FFTW3LibraryDepends-debug.cmake
pylib_fftw3f/lib/cmake/fftw3f/FFTW3LibraryDepends.cmake
pylib_fftw3f/lib/cmake/fftw3f/FFTW3fConfig.cmake
pylib_fftw3f/lib/cmake/fftw3f/FFTW3fConfigVersion.cmake
pylib_fftw3f/lib/pkgconfig/fftw3f.pc
pylib_fftw3f-0.0.6.dist-info/METADATA
pylib_fftw3f-0.0.6.dist-info/WHEEL
pylib_fftw3f-0.0.6.dist-info/top_level.txt
pylib_fftw3f-0.0.6.dist-info/RECORD
